celeste_elevenlabs/__init__.py
celeste_elevenlabs/py.typed
celeste_elevenlabs/text_to_speech/__init__.py
celeste_elevenlabs/text_to_speech/client.py
celeste_elevenlabs/text_to_speech/config.py
celeste_elevenlabs/text_to_speech/parameters.py
celeste_elevenlabs-0.3.6.dist-info/METADATA
celeste_elevenlabs-0.3.6.dist-info/WHEEL
celeste_elevenlabs-0.3.6.dist-info/RECORD
