Metadata-Version: 2.4
Name: celeste-elevenlabs
Version: 0.3.6
Summary: ElevenLabs provider package for Celeste AI
Author-email: Kamilbenkirane <kamil@withceleste.ai>
License: Apache-2.0
Requires-Python: >=3.12
Requires-Dist: celeste-ai
Requires-Dist: httpx
